converge_load_forecasting/__init__.py
converge_load_forecasting/disaggregation.py
converge_load_forecasting/forecasting.py
converge_load_forecasting-0.1.0.dist-info/METADATA
converge_load_forecasting-0.1.0.dist-info/WHEEL
converge_load_forecasting-0.1.0.dist-info/top_level.txt
converge_load_forecasting-0.1.0.dist-info/RECORD
