Metadata-Version: 2.1
Name: converge-load-forecasting
Version: 0.1.0
Author: Seyyed Mahdi Noori Rahim Abadi, Dan Gordon
Author-email: mahdi.noori@anu.edu.au
Requires-Dist: connectorx
Requires-Dist: python-dateutil
Requires-Dist: datetime
Requires-Dist: matplotlib
Requires-Dist: more-itertools
Requires-Dist: multiprocess
Requires-Dist: pandas
Requires-Dist: pyomo
Requires-Dist: skforecast (==0.7.0)
Requires-Dist: sklearn
Requires-Dist: statsmodels
Requires-Dist: tqdm
Requires-Dist: tspiral
Requires-Dist: xgboost
